{
    "organizations": [],
    "uuid": "cacf7fb244a743e697858e1cf95cba2db9dc8978",
    "author": "",
    "url": "https://www.reuters.com/article/brief-new-residential-investment-says-un/brief-new-residential-investment-says-units-entered-into-financing-transaction-idUSFWN1RA0ZP",
    "ord_in_thread": 0,
    "title": "BRIEF-New Residential Investment Says Units Entered Into Financing Transaction",
    "locations": [],
    "highlightText": "",
    "language": "english",
    "persons": [],
    "text": "March 28 (Reuters) - New Residential Investment Corp :\n* NEW RESIDENTIAL INVESTMENT CORP - ON MARCH 22, CO, UNITS ENTERED INTO A FINANCING TRANSACTION - SEC FILING\n* NEW RESIDENTIAL INVESTMENT- UNIT ISSUED $425 MILLION OF BALANCE OF SERVICER ADVANCE RECEIVABLES, DEFERRED SERVICING FEE BACKED VARIABLE FUNDING NOTES Source text - bit.ly/2Gyo0aX Further company coverage:\n ",
    "published": "2018-03-29T01:08:00.000+03:00",
    "crawled": "2018-03-29T01:37:22.011+03:00",
    "highlightTitle": "",
    "preprocessed_text": [
        "march",
        "reuters",
        "new",
        "residential",
        "investment",
        "corp",
        "new",
        "residential",
        "investment",
        "corp",
        "march",
        "co",
        "unit",
        "entered",
        "financing",
        "transaction",
        "sec",
        "filing",
        "new",
        "residential",
        "unit",
        "issued",
        "million",
        "balance",
        "servicer",
        "advance",
        "receivables",
        "deferred",
        "servicing",
        "fee",
        "backed",
        "variable",
        "funding",
        "note",
        "source",
        "text",
        "company",
        "coverage"
    ]
}