{
    "organizations": [],
    "uuid": "c490d55b57c51117072240f672f8f0235936a82d",
    "author": "Reuters Editorial",
    "url": "https://www.reuters.com/article/brief-sodic-to-develop-residential-touri/brief-sodic-to-develop-residential-tourism-project-in-partnership-idUSFWN1QT032",
    "ord_in_thread": 0,
    "title": "BRIEF-SODIC To Develop Residential Tourism Project in Partnership",
    "locations": [],
    "highlightText": "",
    "language": "english",
    "persons": [],
    "text": "March 11 (Reuters) - SIXTH OF OCTOBER DEVELOPMENT AND INVESTMENT CO:\n* SIGNS TWO PARTNERSHIP DEALS TO DEVELOP RESIDENTIAL TOURISM PROJECT ON ABOUT 308 FEDAN PLOTS\n* OWNERS OF PLOTS TO HAVE PARTICIPATION OF 28 PERCENT AND CO 72 PERCENT OF TOTAL REVENUE OF RESIDENTIAL AND COMMERCIAL UNITS\n* EXPECTS TOTAL CUSTOMER CONTRACTS OF PROJECT TO REACH ABOUT EGP 15.2 BILLION DURING 7 YEARS Source: ( bit.ly/2tz1Obh ) Further company coverage:\n ",
    "published": "2018-03-11T15:04:00.000+02:00",
    "crawled": "2018-03-12T13:05:57.005+02:00",
    "highlightTitle": "",
    "preprocessed_text": [
        "march",
        "reuters",
        "sixth",
        "october",
        "development",
        "investment",
        "co",
        "sign",
        "two",
        "partnership",
        "deal",
        "develop",
        "residential",
        "tourism",
        "project",
        "fedan",
        "plot",
        "owner",
        "plot",
        "participation",
        "percent",
        "co",
        "percent",
        "total",
        "revenue",
        "residential",
        "commercial",
        "unit",
        "expects",
        "total",
        "customer",
        "contract",
        "project",
        "reach",
        "egp",
        "billion",
        "year",
        "source",
        "company",
        "coverage"
    ]
}