{
    "organizations": [],
    "uuid": "5b1f113c53a92b5d6a765a433c76a712d3709772",
    "author": "Reuters Editorial",
    "url": "https://www.reuters.com/article/brief-hangzhou-century-to-pay-cash-divid/brief-hangzhou-century-to-pay-cash-dividend-of-0-18-yuan-per-10-shares-for-2017-idUSL3N1RT3ST",
    "ord_in_thread": 0,
    "title": "BRIEF-Hangzhou Century to pay cash dividend of 0.18 yuan per 10 shares (before tax) for 2017",
    "locations": [],
    "highlightText": "",
    "language": "english",
    "persons": [],
    "text": "April 16(Reuters) - Hangzhou Century Co Ltd\n* Says it plans to pay cash dividend of 0.18 yuan per 10 shares (before tax) to shareholders for 2017\nSource text in Chinese: goo.gl/9eMyeV\nFurther company coverage: (Beijing Headline News)\n ",
    "published": "2018-04-16T17:36:00.000+03:00",
    "crawled": "2018-04-17T12:09:05.035+03:00",
    "highlightTitle": "",
    "preprocessed_text": [
        "april",
        "reuters",
        "hangzhou",
        "century",
        "co",
        "ltd",
        "say",
        "plan",
        "pay",
        "cash",
        "dividend",
        "yuan",
        "per",
        "share",
        "tax",
        "shareholder",
        "source",
        "text",
        "chinese",
        "company",
        "coverage",
        "beijing",
        "headline",
        "news"
    ]
}