{
    "organizations": [],
    "uuid": "7821bff04af39f59350226d71e2209b7ef51e642",
    "author": "Reuters Editorial",
    "url": "https://www.reuters.com/article/brief-punjab-national-bank-maintains-mcl/brief-punjab-national-bank-maintains-mclr-across-all-tenors-w-e-f-april-1-idUSFWN1RE066",
    "ord_in_thread": 0,
    "title": "BRIEF-Punjab National Bank Maintains MCLR Across All Tenors w.e.f. April 1",
    "locations": [],
    "highlightText": "",
    "language": "english",
    "persons": [],
    "text": "April 2 (Reuters) - Punjab National Bank:\n* SAYS CO MAINTAINS MCLR ACROSS ALL TENORS W.E.F. APRIL 1 Source text - bit.ly/2JctBST Further company coverage:\n ",
    "published": "2018-04-02T11:20:00.000+03:00",
    "crawled": "2018-04-02T20:44:27.009+03:00",
    "highlightTitle": "",
    "preprocessed_text": [
        "april",
        "reuters",
        "punjab",
        "national",
        "bank",
        "say",
        "co",
        "maintains",
        "mclr",
        "across",
        "tenor",
        "april",
        "source",
        "text",
        "company",
        "coverage"
    ]
}