{
    "organizations": [],
    "uuid": "d63927f26c2330e9d0146746d77aad551b0aebcb",
    "author": "Daphne Merkin",
    "url": "https://www.wsj.com/articles/review-martin-amis-and-the-rub-of-time-1518211944",
    "ord_in_thread": 0,
    "title": "Review: Martin Amis and ‘The Rub of Time’",
    "locations": [],
    "highlightText": "",
    "language": "english",
    "persons": [],
    "text": "Certitude would seem to be a welcome thing in a critic; it lends his opinions ballast and force. And yet, while reading Martin Amis’s latest collection of essays, “The Rub of Time,” I found myself longing for a little less of it, and for a few grace notes of tentativeness, a soupçon of doubt. Perhaps this is too much to ask of a writer who, from a young age, has been something of a rock star in his home town of London, both as the heir to literary celebrity (his father was Kingsley Amis, his stepmother Elizabeth Jane Howard) and as a prolific man of letters (Mr. Amis published three novels before he was 30 while working... ",
    "published": "2018-02-10T00:32:00.000+02:00",
    "crawled": "2018-02-19T23:58:58.003+02:00",
    "highlightTitle": "",
    "preprocessed_text": [
        "certitude",
        "would",
        "seem",
        "welcome",
        "thing",
        "critic",
        "lends",
        "opinion",
        "ballast",
        "force",
        "yet",
        "reading",
        "martin",
        "amis",
        "latest",
        "collection",
        "essay",
        "rub",
        "time",
        "found",
        "longing",
        "little",
        "less",
        "grace",
        "note",
        "tentativeness",
        "soupçon",
        "doubt",
        "perhaps",
        "much",
        "ask",
        "writer",
        "young",
        "age",
        "something",
        "rock",
        "star",
        "home",
        "town",
        "london",
        "heir",
        "literary",
        "celebrity",
        "father",
        "kingsley",
        "amis",
        "stepmother",
        "elizabeth",
        "jane",
        "howard",
        "prolific",
        "man",
        "letter",
        "amis",
        "published",
        "three",
        "novel",
        "working"
    ]
}