{
    "organizations": [],
    "uuid": "fd89b9ed4270f6cf7be423df8649a60b726cefcc",
    "author": "Reuters Editorial",
    "url": "https://www.reuters.com/article/olympics-freestyle-skiing-men-results/olympics-freestyle-skiing-mens-halfpipe-final-results-idUSISS920056",
    "ord_in_thread": 0,
    "title": "UPDATE 2-Olympics-Freestyle Skiing-Men's halfpipe final results",
    "locations": [],
    "highlightText": "",
    "language": "english",
    "persons": [],
    "text": "Feb 22 (Gracenote) - Olympic freestyle skiing men's halfpipe final results in Pyeongchang on Thursday. 1. David Wise (U.S.) 97.20 points 2. Alex Ferreira (U.S.) 96.40 3. Nico Porteous (New Zealand) 94.80 4. Beau-James Wells (New Zealand) 91.60 5. Noah Bowman (Canada) 89.40 6. Mike Riddle (Canada) 85.40 7. Aaron Blunck (U.S.) 84.80 8. Andreas Gohl (Austria) 68.80 9. Torin Yater-Wallace (U.S.) 65.20 10. Thomas Krief (France) 9.80 11. Kevin Rolland (France) 6.40 12. Byron Wells (New Zealand) DNS\n ",
    "published": "2018-02-22T10:56:00.000+02:00",
    "crawled": "2018-02-22T17:59:35.049+02:00",
    "highlightTitle": "",
    "preprocessed_text": [
        "feb",
        "gracenote",
        "olympic",
        "freestyle",
        "skiing",
        "men",
        "halfpipe",
        "final",
        "result",
        "pyeongchang",
        "thursday",
        "david",
        "wise",
        "point",
        "alex",
        "ferreira",
        "nico",
        "porteous",
        "new",
        "zealand",
        "well",
        "new",
        "zealand",
        "noah",
        "bowman",
        "canada",
        "mike",
        "riddle",
        "canada",
        "aaron",
        "blunck",
        "andreas",
        "gohl",
        "austria",
        "torin",
        "thomas",
        "krief",
        "france",
        "kevin",
        "rolland",
        "france",
        "byron",
        "well",
        "new",
        "zealand",
        "dns"
    ]
}