{
    "organizations": [],
    "uuid": "81e8c8db3ba7888bfe553ac6ff39bf5df7f369e5",
    "author": "cnbc.com",
    "url": "http://www.cnbc.com/2018/02/13/globe-newswire-annual-general-meeting-in-alk-abella-as-on-12-march-2018.html",
    "ord_in_thread": 0,
    "title": "Annual General Meeting in ALK-Abelló A/S on 12 March 2018",
    "locations": [],
    "highlightText": "",
    "language": "english",
    "persons": [],
    "text": "ALK ( ALKB:DC / OMX: ALK B / AKABY / AKBLF ): The annual general meeting of ALK-Abelló A/S will take place on Monday 12 March 2018 at 16:00 (CET) at ALK-Abelló A/S, 1 Bøge Allé, 2970 Hørsholm, Denmark. The agenda of the meeting including the complete proposals from the Board of Directors to the AGM is attached.\nALK-Abelló A/S\nFor further information please contact:\nInvestor Relations : Per Plotnikof, tel. +45 4574 7527, mobile +45 2261 2525\nMedia: Jeppe Ilkjær, tel. +45 7877 4532, mobile +45 3050 2014\nAbout ALK\nALK is a global specialty pharmaceutical company focused on allergy and allergic asthma. It markets allergy immunotherapy treatments and other products and services for people with allergy and allergy doctors. Headquartered in Hørsholm, Denmark, ALK employs around 2,300 people worldwide and is listed on Nasdaq Copenhagen. Find more information at www.alk.net .\nAttachments:\nhttp://www.globenewswire.com/NewsRoom/AttachmentNg/fdfb0e5d-f82b-4a25-b5ed-1bff3cec6fb5\nSource: ALK-Abello",
    "published": "2018-02-13T15:55:00.000+02:00",
    "crawled": "2018-02-13T17:23:12.000+02:00",
    "highlightTitle": "",
    "preprocessed_text": [
        "alk",
        "alkb",
        "dc",
        "omx",
        "alk",
        "b",
        "akaby",
        "akblf",
        "annual",
        "general",
        "meeting",
        "take",
        "place",
        "monday",
        "march",
        "cet",
        "bøge",
        "allé",
        "hørsholm",
        "denmark",
        "agenda",
        "meeting",
        "including",
        "complete",
        "proposal",
        "board",
        "director",
        "agm",
        "attached",
        "information",
        "please",
        "contact",
        "investor",
        "relation",
        "per",
        "plotnikof",
        "tel",
        "mobile",
        "medium",
        "jeppe",
        "ilkjær",
        "tel",
        "mobile",
        "alk",
        "alk",
        "global",
        "specialty",
        "pharmaceutical",
        "company",
        "focused",
        "allergy",
        "allergic",
        "asthma",
        "market",
        "allergy",
        "immunotherapy",
        "treatment",
        "product",
        "service",
        "people",
        "allergy",
        "allergy",
        "doctor",
        "headquartered",
        "hørsholm",
        "denmark",
        "alk",
        "employ",
        "around",
        "people",
        "worldwide",
        "listed",
        "nasdaq",
        "copenhagen",
        "find",
        "information",
        "attachment",
        "http",
        "source"
    ]
}