{
    "organizations": [],
    "uuid": "d7e6186da81e252e50466fd1e984bfa029b924fa",
    "author": "Reuters Editorial",
    "url": "https://www.reuters.com/article/brief-metro-reports-q1-eps-of-c567/brief-metro-reports-q1-eps-of-c5-67-idUSASB0C2Y2",
    "ord_in_thread": 0,
    "title": "BRIEF-Metro Reports Q1 EPS Of C$5.67",
    "locations": [],
    "highlightText": "",
    "language": "english",
    "persons": [],
    "text": "Jan 30 (Reuters) - Metro Inc:\n* METRO REPORTS 2018 FIRST QUARTER RESULTS * Q1 ADJUSTED EARNINGS PER SHARE C$0.67 * Q1 EARNINGS PER SHARE C$5.67 * Q1 SALES ROSE 4.7 PERCENT TO C$3.112 BILLION * Q1 SAME STORE SALES ROSE 3.4 PERCENT * Q1 EARNINGS PER SHARE VIEW C$0.59 -- THOMSON REUTERS I/B/E/S\n* METRO - DECLARED A QUARTERLY DIVIDEND OF $0.18/SHARE PAYABLE ON MARCH 13, 2018, INCREASE OF 10.8% OVER DIVIDEND DECLARED FOR SAME QUARTER LAST YEAR Source text for Eikon: Further company coverage:\n ",
    "published": "2018-01-30T20:07:00.000+02:00",
    "crawled": "2018-01-31T16:49:59.013+02:00",
    "highlightTitle": "",
    "preprocessed_text": [
        "jan",
        "reuters",
        "metro",
        "inc",
        "metro",
        "report",
        "first",
        "quarter",
        "result",
        "q1",
        "adjusted",
        "earnings",
        "per",
        "share",
        "c",
        "q1",
        "earnings",
        "per",
        "share",
        "c",
        "q1",
        "sale",
        "rose",
        "percent",
        "c",
        "billion",
        "q1",
        "store",
        "sale",
        "rose",
        "percent",
        "q1",
        "earnings",
        "per",
        "share",
        "view",
        "c",
        "thomson",
        "reuters",
        "metro",
        "declared",
        "quarterly",
        "dividend",
        "payable",
        "march",
        "increase",
        "dividend",
        "declared",
        "quarter",
        "last",
        "year",
        "source",
        "text",
        "eikon",
        "company",
        "coverage"
    ]
}